code_data_share_for_python-0.0.1.dist-info/WHEEL
code_data_share_for_python-0.0.1.dist-info/LICENSE
code_data_share_for_python-0.0.1.dist-info/METADATA
code_data_share_for_python-0.0.1.dist-info/top_level.txt
code_data_share_for_python-0.0.1.dist-info/RECORD
cds/dump.py
cds/__init__.py
code_data_share_for_python-0.0.1.data/data/lib/python3.10/site-packages/_cds.cpython-310-x86_64-linux-gnu.so
code_data_share_for_python-0.0.1.data/data/lib/python3.10/site-packages/pycds.pth
